whale_back_bone/__init__.py
whale_back_bone/mysql_connection/__init__.py
whale_back_bone/mysql_connection/db_connections.py
whale_back_bone-1.1.0.dist-info/WHEEL
whale_back_bone-1.1.0.dist-info/METADATA
whale_back_bone-1.1.0.dist-info/RECORD
